apiens/__init__.py
apiens/di/__init__.py
apiens/di/const.py
apiens/di/defs.py
apiens/di/exc.py
apiens/di/injector.py
apiens/di/markers.py
apiens/di/util.py
apiens/errors.py
apiens/errors_default.py
apiens/operations.py
apiens/signature.py
apiens/testing/__init__.py
apiens/testing/object_match.py
apiens/testing/successful_mixin.py
apiens/tools/__init__.py
apiens/tools/fastapi/__init__.py
apiens/tools/fastapi/class_based_view/__init__.py
apiens/tools/fastapi/class_based_view/class_based_crud.py
apiens/tools/fastapi/class_based_view/class_based_view.py
apiens/tools/fastapi/class_based_view/patch_func.py
apiens/tools/titled_enum.py
apiens/util/__init__.py
apiens/util/decomarker.py
apiens/util/documented_function.py
apiens/via/__init__.py
apiens/via/fastapi/__init__.py
apiens/via/fastapi/error_schema.py
apiens/via/fastapi/fastapi_route.py
apiens/via/fastapi/query_object.py
apiens/via/fastapi/router.py
apiens/views/__init__.py
apiens/views/crud/__init__.py
apiens/views/crud/crud_settings.py
apiens/views/crud/crud_signals.py
apiens/views/crud/crudbase.py
apiens/views/crud/defs.py
apiens/views/crud/instance_history_proxy.py
apiens/views/crud/pg_integrity_error.py
apiens/views/mongoquery_crud/__init__.py
apiens/views/mongoquery_crud/defs.py
apiens/views/mongoquery_crud/mongocrud_settings.py
apiens/views/mongoquery_crud/mongocrudbase.py
apiens-1.0.1.dist-info/LICENSE
apiens-1.0.1.dist-info/WHEEL
apiens-1.0.1.dist-info/METADATA
apiens-1.0.1.dist-info/RECORD
