Metadata-Version: 2.1
Name: apiens
Version: 1.0.1
Summary: Business-logic layer for your API
Home-page: https://github.com/kolypto/py-apiens
Author: Mark Vartanyan
Author-email: kolypto@gmail.com
Requires-Python: >=3.8,<4.0
Classifier: Programming Language :: Python :: 3
Classifier: Programming Language :: Python :: 3.8
Classifier: Programming Language :: Python :: 3.9
Provides-Extra: crud
Provides-Extra: fastapi
Requires-Dist: PyYAML (>=5.3.1,<6.0.0)
Requires-Dist: blinker (>=1.4,<2.0); extra == "crud"
Requires-Dist: docstring-parser (>=0.7.3,<0.8.0)
Requires-Dist: fastapi (>=0.61.1,<0.62.0); extra == "fastapi"
Requires-Dist: mongosql (>=2.0.11,<3.0.0); extra == "crud"
Requires-Dist: pydantic (>=1.6.1,<2.0.0); extra == "crud"
Requires-Dist: sa2schema (>=0.1.3,<0.2.0); extra == "crud"
Requires-Dist: sqlalchemy (>=1.3.19,<2.0.0); extra == "crud"
Project-URL: Repository, https://github.com/kolypto/py-apiens
